opentelemetry/sdk/extension/prometheus_multiprocess/__init__.py
opentelemetry/sdk/extension/prometheus_multiprocess/provider.py
opentelemetry/sdk/extension/prometheus_multiprocess/registry.py
opentelemetry_sdk_extension_prometheus_multiprocess-1.2.3.dist-info/METADATA
opentelemetry_sdk_extension_prometheus_multiprocess-1.2.3.dist-info/WHEEL
opentelemetry_sdk_extension_prometheus_multiprocess-1.2.3.dist-info/RECORD
