Metadata-Version: 2.3
Name: opentelemetry-sdk-extension-prometheus-multiprocess
Version: 1.2.3
Author-email: Zeit Online <zon-backend@zeit.de>
Requires-Dist: opentelemetry-exporter-prometheus
Requires-Dist: opentelemetry-sdk>=1.30.0.dev0
Requires-Dist: requests
Provides-Extra: test
Requires-Dist: pytest; extra == 'test'
